subaudit/__init__.py
subaudit/py.typed
subaudit-0.1.0.dist-info/LICENSE
subaudit-0.1.0.dist-info/METADATA
subaudit-0.1.0.dist-info/WHEEL
subaudit-0.1.0.dist-info/RECORD
