Metadata-Version: 2.1
Name: subaudit
Version: 0.1.0
Summary: Subscribe and unsubscribe for specific audit events
Home-page: https://github.com/EliahKagan/subaudit
License: 0BSD
Keywords: audit,auditing,events,subscribe,unsubscribe
Author: Eliah Kagan
Author-email: degeneracypressure@gmail.com
Requires-Python: >=3.7,<4.0
Classifier: Development Status :: 3 - Alpha
Classifier: Intended Audience :: Developers
Classifier: License :: OSI Approved
Classifier: License :: Other/Proprietary License
Classifier: Programming Language :: Python :: 3
Classifier: Programming Language :: Python :: 3.7
Classifier: Programming Language :: Python :: 3.8
Classifier: Programming Language :: Python :: 3.9
Classifier: Programming Language :: Python :: 3.10
Classifier: Programming Language :: Python :: 3.11
Classifier: Topic :: Software Development :: Testing
Classifier: Typing :: Typed
Requires-Dist: sysaudit (>=0.3.0,<0.4.0) ; python_version >= "3.7" and python_version < "3.8"
Project-URL: Repository, https://github.com/EliahKagan/subaudit
